{
  "main": {
    "id": "5880edc4a4ce5f68",
    "type": "split",
    "children": [
      {
        "id": "45f50e520fc3c9fc",
        "type": "tabs",
        "children": [
          {
            "id": "eb3f5f5e88384d11",
            "type": "leaf",
            "state": {
              "type": "empty",
              "state": {}
            }
          }
        ]
      }
    ],
    "direction": "vertical"
  },
  "left": {
    "id": "5c76c8b6ba563908",
    "type": "mobile-drawer",
    "children": [
      {
        "id": "7ebd6aa0bbdd238f",
        "type": "leaf",
        "state": {
          "type": "recent-files",
          "state": {}
        }
      },
      {
        "id": "4b0f7040d04b6f7e",
        "type": "leaf",
        "state": {
          "type": "file-explorer",
          "state": {
            "sortOrder": "alphabetical"
          }
        }
      },
      {
        "id": "f3538f45e61f5789",
        "type": "leaf",
        "state": {
          "type": "search",
          "state": {
            "query": "",
            "matchingCase": false,
            "explainSearch": false,
            "collapseAll": false,
            "extraContext": false,
            "sortOrder": "alphabetical"
          }
        }
      },
      {
        "id": "a2d121c9c71e2da1",
        "type": "leaf",
        "state": {
          "type": "tag",
          "state": {
            "sortOrder": "frequency",
            "useHierarchy": true
          }
        }
      },
      {
        "id": "a7d74913226f194d",
        "type": "leaf",
        "state": {
          "type": "bookmarks",
          "state": {}
        }
      }
    ],
    "currentTab": 1
  },
  "right": {
    "id": "f922990d6fc8a174",
    "type": "mobile-drawer",
    "children": [
      {
        "id": "62f730f1f4dc0eec",
        "type": "leaf",
        "state": {
          "type": "backlink",
          "state": {
            "collapseAll": false,
            "extraContext": false,
            "sortOrder": "alphabetical",
            "showSearch": false,
            "searchQuery": "",
            "backlinkCollapsed": false,
            "unlinkedCollapsed": true
          }
        }
      },
      {
        "id": "8be27db7ffe8a6e3",
        "type": "leaf",
        "state": {
          "type": "outgoing-link",
          "state": {
            "linksCollapsed": false,
            "unlinkedCollapsed": true
          }
        }
      },
      {
        "id": "0f21be593d9928a4",
        "type": "leaf",
        "state": {
          "type": "outline",
          "state": {}
        }
      }
    ],
    "currentTab": 0
  },
  "left-ribbon": {
    "hiddenItems": {
      "table-editor-obsidian:Advanced Tables Toolbar": false,
      "switcher:Open quick switcher": false,
      "graph:Open graph view": false,
      "canvas:Create new canvas": false,
      "daily-notes:Open today's daily note": false,
      "templates:Insert template": false,
      "command-palette:Open command palette": false
    }
  },
  "active": "eb3f5f5e88384d11",
  "lastOpenFiles": []
}